navin/__init__.py
navin/cli.py
navin/server.py
navin/static/style.css
navin-0.1.dist-info/METADATA
navin-0.1.dist-info/WHEEL
navin-0.1.dist-info/entry_points.txt
navin-0.1.dist-info/top_level.txt
navin-0.1.dist-info/RECORD
