Metadata-Version: 2.4
Name: navin
Version: 0.1
Summary: A simple local server with static HTML/CSS, started via 'navin runserver' command.
Author-email: Your Name <your.email@example.com>
Requires-Python: >=3.7
Requires-Dist: flask>=2.0
